nfl/__init__.py
nfl/config.py
nfl/metrics.py
nfl/plots.py
nfl/visuals.py
nfl_tracks-1.3.1.dist-info/licenses/LICENSE
nfl_tracks-1.3.1.dist-info/METADATA
nfl_tracks-1.3.1.dist-info/WHEEL
nfl_tracks-1.3.1.dist-info/top_level.txt
nfl_tracks-1.3.1.dist-info/RECORD
