Metadata-Version: 2.4
Name: nfl_tracks
Version: 1.3.1
Summary: Python library written on top of matplotlib library for customizable nfl charts
Home-page: https://github.com/shammeer-s/nfl-tracks
Author: Mohammed Shammeer
Author-email: mohammedshammeer.s@gmail.com
Keywords: nfl,visualization,animated charts
Classifier: Programming Language :: Python :: 3
Classifier: Development Status :: 3 - Alpha
Classifier: Intended Audience :: Developers
Classifier: Topic :: Software Development :: Build Tools
Classifier: License :: OSI Approved :: MIT License
Classifier: Operating System :: OS Independent
License-File: LICENSE
Requires-Dist: pandas
Requires-Dist: matplotlib
Requires-Dist: scipy
Requires-Dist: seaborn
Provides-Extra: dev
Requires-Dist: pytest; extra == "dev"
Dynamic: author
Dynamic: author-email
Dynamic: classifier
Dynamic: description
Dynamic: description-content-type
Dynamic: home-page
Dynamic: keywords
Dynamic: license-file
Dynamic: provides-extra
Dynamic: requires-dist
Dynamic: summary
